<mapreducescript scriptid="customscript_nst_mr_auto_query_int">
  <description>Map reduce script testing script using query to object.</description>
  <isinactive>F</isinactive>
  <name>NST MR Auto Query Integration</name>
  <notifyadmins>F</notifyadmins>
  <notifyemails></notifyemails>
  <notifyowner>F</notifyowner>
  <notifyuser>F</notifyuser>
  <scriptfile>[/SuiteScripts/ns-tools-integration/MapReduce/NST_MR_Auto_Query_Integration.js]</scriptfile>
  <scriptdeployments>
    <scriptdeployment scriptid="customdeploy_nst_mr_aq_dep_1">
      <allemployees>F</allemployees>
      <allpartners>F</allpartners>
      <allroles>T</allroles>
      <audslctrole></audslctrole>
      <eventtype></eventtype>
      <isdeployed>T</isdeployed>
      <isonline>F</isonline>
      <loglevel>DEBUG</loglevel>
      <runasrole></runasrole>
      <status>TESTING</status>
      <title>NST MR Auto Query Integration Deploy 1</title>
    </scriptdeployment>
  </scriptdeployments>
</mapreducescript>
